agin/__init__.py
agin/agin.py
aigic-1.0.4.dist-info/METADATA
aigic-1.0.4.dist-info/WHEEL
aigic-1.0.4.dist-info/top_level.txt
aigic-1.0.4.dist-info/RECORD
