Metadata-Version: 2.1
Name: aigic
Version: 1.0.4
Summary: agin python SDK
Author: 
Author-email: 
Requires-Dist: http.client
